unicode_string_to_identifier.py
unicode_string_to_identifier-0.1.0a0.dist-info/METADATA
unicode_string_to_identifier-0.1.0a0.dist-info/WHEEL
unicode_string_to_identifier-0.1.0a0.dist-info/top_level.txt
unicode_string_to_identifier-0.1.0a0.dist-info/RECORD
