Metadata-Version: 2.4
Name: unicode-string-to-identifier
Version: 0.1.0a0
Summary: A tool that converts arbitrary text (like user input or file names) into valid Python identifiers while preserving as much of the original meaning as possible.
Author-email: Jifeng Wu <jifengwu2k@gmail.com>
License-Expression: MIT
Project-URL: Homepage, https://github.com/jifengwu2k/unicode-string-to-identifier
Project-URL: Bug Tracker, https://github.com/jifengwu2k/unicode-string-to-identifier/issues
Classifier: Programming Language :: Python :: 2
Classifier: Programming Language :: Python :: 3
Classifier: Operating System :: OS Independent
Requires-Python: >=2
